package_test1/__init__.py
package_test1/core.py
package_test1/log.py
package_test1/server.py
package_test1-0.1.1.dist-info/METADATA
package_test1-0.1.1.dist-info/WHEEL
package_test1-0.1.1.dist-info/top_level.txt
package_test1-0.1.1.dist-info/RECORD
